{"dna":"030000010203000601","name":"#4","description":"NFT creato dai piskelli","image":"https://ipfs.moralis.io:2053/ipfs/QmcsRtF6VkHPfhG13vsARCFEewYDweZDu1Ezz34Dpjo7Yt/images/0000000000000000000000000000000000000000000000000000000000000004.png","edition":4,"date":1643562178798,"attributes":[{"name":"Background_Lava","rarity":"original"},{"name":"Body_Alien","rarity":"original"},{"name":"Eyes_Angry","rarity":"original"},{"name":"Head_Gold","rarity":"original"},{"name":"Headwear_Bowler","rarity":"original"},{"name":"Mouth_Lock Beard","rarity":"original"},{"name":"Nose_Common","rarity":"original"},{"name":"Outfit_Shirt with holes","rarity":"original"},{"name":"Sunglasses_Cateyes","rarity":"original"}]}